manim_data_structures/__init__.py
manim_data_structures/m_array.py
manim_data_structures/m_enum.py
manim_data_structures/m_variable.py
manim_data_structures-0.1.7.dist-info/entry_points.txt
manim_data_structures-0.1.7.dist-info/LICENSE.md
manim_data_structures-0.1.7.dist-info/WHEEL
manim_data_structures-0.1.7.dist-info/METADATA
manim_data_structures-0.1.7.dist-info/RECORD
