Metadata-Version: 2.1
Name: manim-data-structures
Version: 0.1.7
Summary: A Manim implementation for data structures
Home-page: https://github.com/drageelr/manim-data-structures
Author: Hammad Nasir
Author-email: hammadn99@gmail.com
Requires-Python: >=3.7,<3.11
Classifier: Programming Language :: Python :: 3
Classifier: Programming Language :: Python :: 3.7
Classifier: Programming Language :: Python :: 3.8
Classifier: Programming Language :: Python :: 3.9
Classifier: Programming Language :: Python :: 3.10
Requires-Dist: manim (>=0.16.0)
Project-URL: Bug Tracker, https://github.com/drageelr/manim-data-structures/issues
Project-URL: Changelog, https://github.com/drageelr/manim-data-structures/blob/main/CHANGELOG.md
Project-URL: Documentation, https://manim-data-structures.readthedocs.io/en/latest/
Project-URL: Repository, https://github.com/drageelr/manim-data-structures
